{"id":"aVJ65Boy-aU","title":"هل الاستماع إلى الأغاني حرام؟","description":"أسئلة المتابعين | أ.د. يسري جبر \n#يسري_جبر#أسئلة#الأغاني#الحجاب \n00:00 - هل الاستماع إلى الأغاني حرام؟\n06:29 - هل عدم لبس الحجاب من الكبائر؟\n08:01 - هل يجوز خروج المخطوبين بمفردهم؟\n09:11 - هل يجب إخراج الزكاة على الذهب والفضة؟","publishedAt":"2022-05-05T18:00:00Z","duration":"PT11M40S","thumbnail":"https://i.ytimg.com/vi/aVJ65Boy-aU/mqdefault.jpg","viewCount":"21296","likeCount":"1194","commentCount":"100","playlistId":"PLEkQk5xrP-tm8ZIu74nTOZN9KJUJu416J","playlistName":"مقاطع مُهمَّة (يُسريَّات) أ.د. يسري جبر","category":"متنوع","nav":{"prev":"TwtgQDgfrSQ","next":"J5fwRVtLIR4","index":382,"total":560}}