{"id":"RXa4VbAx1JA","title":"409- فضل حِلَقِ الذِكر والندب على ملازمتها والنهي عن مفارقتها لغير عذر - شرح دليل الفالحين","description":"شرح كتاب دليل الفالحين لطرق رياض الصالحين للشيخ محمد بن علَّان الصِّدِّيقيّ الشافِعيّ الأشعريّ المَكِّي وهو شرحٌ  لكتاب رياض الصالحين للإمام مُحيي الدِّين أبي زكريا يحيى بن شرف النوويّ رضي الله تعالى عنهما - \nالمجلد الرابع\n\nالكتاب الخامس عشر: كتاب الأذكار\n\nالمجلس (409): فضل حِلَقِ الذِكر والندب على ملازمتها والنهي عن مفارقتها لغير عذر\n\n23 جمادى الآخرة 1444 الموافق\n\n16 - 1 - 2022\n\nبمسجد الأشراف بالمقط","publishedAt":"2023-03-09T05:00:16Z","duration":"PT30M5S","thumbnail":"https://i.ytimg.com/vi/RXa4VbAx1JA/mqdefault.jpg","viewCount":"1806","likeCount":"107","commentCount":"11","playlistId":"PLEkQk5xrP-tkc9DXvSLguqX5-FYp6ASR4","playlistName":"دليل الفالحين لطرق رياض الصالحين","category":"متنوع","nav":{"prev":"cIpcCFQwEUU","next":"5mhTZ4lK7iQ","index":408,"total":504}}