{"items":[{"id":"cQ5d6-49ZKc","title":"صحيح الإمام البخاري رضي الله عنه -كتاب الرقاق باب يدخل الجنة سبعون ألفا بغير حساب (13) د.يسري جبر","publishedAt":"2017-09-19T17:44:59Z","duration":"PT52M14S","thumbnail":"https://i.ytimg.com/vi/cQ5d6-49ZKc/mqdefault.jpg","viewCount":"412","playlistId":"PLEkQk5xrP-tmJuzaj4GWRenFoFx9gdbFX","playlistName":"شرح كتاب صحيح الإمام البخاري رضي الله تعالى عنه   أ.د. يسرى جبر","category":"حديث"},{"id":"4QXeIJjMbEU","title":"صحيح الإمام البخاري رضي الله عنه -كتاب الرقاق باب \"الا يظن اولئك انهم مبعوثون\" (12) د.يسري جبر","publishedAt":"2017-09-19T05:06:33Z","duration":"PT31M24S","thumbnail":"https://i.ytimg.com/vi/4QXeIJjMbEU/mqdefault.jpg","viewCount":"147","playlistId":"PLEkQk5xrP-tmJuzaj4GWRenFoFx9gdbFX","playlistName":"شرح كتاب صحيح الإمام البخاري رضي الله تعالى عنه   أ.د. يسرى جبر","category":"حديث"},{"id":"dYFsmsQmYak","title":"صحيح الإمام البخاري رضي الله عنه - كتاب الرقاق باب نفخ الصور(11) د.يسري جبر","publishedAt":"2017-09-18T12:12:33Z","duration":"PT58M19S","thumbnail":"https://i.ytimg.com/vi/dYFsmsQmYak/mqdefault.jpg","viewCount":"253","playlistId":"PLEkQk5xrP-tmJuzaj4GWRenFoFx9gdbFX","playlistName":"شرح كتاب صحيح الإمام البخاري رضي الله تعالى عنه   أ.د. يسرى جبر","category":"حديث"},{"id":"piEUVIPnH6w","title":"صحيح الإمام البخاري رضي الله عنه - كتاب الرقاق باب من أحب لقاء الله أحب الله لقاءه (10) د.يسري جبر","publishedAt":"2017-09-10T21:02:21Z","duration":"PT37M40S","thumbnail":"https://i.ytimg.com/vi/piEUVIPnH6w/mqdefault.jpg","viewCount":"284","playlistId":"PLEkQk5xrP-tmJuzaj4GWRenFoFx9gdbFX","playlistName":"شرح كتاب صحيح الإمام البخاري رضي الله تعالى عنه   أ.د. يسرى جبر","category":"حديث"},{"id":"qAqArrbJzos","title":"شرح صحيح الإمام البخاري رضي الله عنه - كتاب الرقاق باب رفع الأمانة (9) د.يسري جبر","publishedAt":"2017-09-03T18:16:58Z","duration":"PT58M15S","thumbnail":"https://i.ytimg.com/vi/qAqArrbJzos/mqdefault.jpg","viewCount":"169","playlistId":"PLEkQk5xrP-tmJuzaj4GWRenFoFx9gdbFX","playlistName":"شرح كتاب صحيح الإمام البخاري رضي الله تعالى عنه   أ.د. يسرى جبر","category":"حديث"},{"id":"-tCXdA3lML8","title":"شرح صحيح الإمام البخاري رضي الله عنه - كتاب الرقاق باب من همَّ بحسنة أو بسيئة (8) د.يسري جبر","publishedAt":"2017-08-29T18:35:41Z","duration":"PT39M59S","thumbnail":"https://i.ytimg.com/vi/-tCXdA3lML8/mqdefault.jpg","viewCount":"148","playlistId":"PLEkQk5xrP-tmJuzaj4GWRenFoFx9gdbFX","playlistName":"شرح كتاب صحيح الإمام البخاري رضي الله تعالى عنه   أ.د. يسرى جبر","category":"حديث"},{"id":"LxBp0Iej6Ik","title":"شرح صحيح الإمام البخاري رضي الله عنه - كتاب الرقاق باب البكاء من خشية الله (7) د.يسري جبر","publishedAt":"2017-08-26T06:40:14Z","duration":"PT58M7S","thumbnail":"https://i.ytimg.com/vi/LxBp0Iej6Ik/mqdefault.jpg","viewCount":"490","playlistId":"PLEkQk5xrP-tmJuzaj4GWRenFoFx9gdbFX","playlistName":"شرح كتاب صحيح الإمام البخاري رضي الله تعالى عنه   أ.د. يسرى جبر","category":"حديث"},{"id":"5p5mQ2mRCBo","title":"شرح صحيح الإمام البخاري رضي الله عنه - كتاب الرقاق باب القصد والمداومة على العمل (6) د.يسري جبر","publishedAt":"2017-08-15T03:34:14Z","duration":"PT1H14M24S","thumbnail":"https://i.ytimg.com/vi/5p5mQ2mRCBo/mqdefault.jpg","viewCount":"364","playlistId":"PLEkQk5xrP-tmJuzaj4GWRenFoFx9gdbFX","playlistName":"شرح كتاب صحيح الإمام البخاري رضي الله تعالى عنه   أ.د. يسرى جبر","category":"حديث"},{"id":"HL9jqjoRRsY","title":"صحيح الإمام البخاري  كتاب الرقاق كيف كان عيش النبي صلى الله عليه وآله وسلم (5) د.يسري جبر","publishedAt":"2017-08-14T14:49:17Z","duration":"PT40M31S","thumbnail":"https://i.ytimg.com/vi/HL9jqjoRRsY/mqdefault.jpg","viewCount":"374","playlistId":"PLEkQk5xrP-tmJuzaj4GWRenFoFx9gdbFX","playlistName":"شرح كتاب صحيح الإمام البخاري رضي الله تعالى عنه   أ.د. يسرى جبر","category":"حديث"},{"id":"Be1cKme0fP4","title":"صحيح الإمام البخاري كتاب الرقاق قول النبي صلى الله عليه وآله وسلم هذا المال خضرة حلوة (4) د.يسري جبر","publishedAt":"2017-08-08T02:57:57Z","duration":"PT55M16S","thumbnail":"https://i.ytimg.com/vi/Be1cKme0fP4/mqdefault.jpg","viewCount":"285","playlistId":"PLEkQk5xrP-tmJuzaj4GWRenFoFx9gdbFX","playlistName":"شرح كتاب صحيح الإمام البخاري رضي الله تعالى عنه   أ.د. يسرى جبر","category":"حديث"},{"id":"iXCiraJB17Q","title":"شرح صحيح الإمام البخاري رضي الله عنه - كتاب الرقاق - المجلس الثالث د.يسري جبر","publishedAt":"2017-08-07T15:05:44Z","duration":"PT52M50S","thumbnail":"https://i.ytimg.com/vi/iXCiraJB17Q/mqdefault.jpg","viewCount":"151","playlistId":"PLEkQk5xrP-tmJuzaj4GWRenFoFx9gdbFX","playlistName":"شرح كتاب صحيح الإمام البخاري رضي الله تعالى عنه   أ.د. يسرى جبر","category":"حديث"},{"id":"YQuTBcWnImQ","title":"شرح صحيح الإمام البخاري رضي الله عنه -  كتاب الرقاق (بابٌ في الأمل وطوله) المجلس الثاني د.يسري جبر","publishedAt":"2017-08-01T02:33:53Z","duration":"PT1H13M49S","thumbnail":"https://i.ytimg.com/vi/YQuTBcWnImQ/mqdefault.jpg","viewCount":"310","playlistId":"PLEkQk5xrP-tmJuzaj4GWRenFoFx9gdbFX","playlistName":"شرح كتاب صحيح الإمام البخاري رضي الله تعالى عنه   أ.د. يسرى جبر","category":"حديث"},{"id":"sQ2Xd_nyFZw","title":"صحيح البخاري ختام كتاب الدعوات وبداية كتاب الرقاق(الصحة والفراغ ولا عيش إلا عيش الآخرة) د.يسري جبر","publishedAt":"2017-07-30T16:08:27Z","duration":"PT52M41S","thumbnail":"https://i.ytimg.com/vi/sQ2Xd_nyFZw/mqdefault.jpg","viewCount":"222","playlistId":"PLEkQk5xrP-tmJuzaj4GWRenFoFx9gdbFX","playlistName":"شرح كتاب صحيح الإمام البخاري رضي الله تعالى عنه   أ.د. يسرى جبر","category":"حديث"},{"id":"GrzoEUgW0Ms","title":"باب قول النبي صلى الله عليه وآله وسلم \"اللهم اغفر لي ما قدمت وما أخرت\" المجلس السابع د. يسري جبر","publishedAt":"2017-07-29T06:47:55Z","duration":"PT52M5S","thumbnail":"https://i.ytimg.com/vi/GrzoEUgW0Ms/mqdefault.jpg","viewCount":"534","playlistId":"PLEkQk5xrP-tmJuzaj4GWRenFoFx9gdbFX","playlistName":"شرح كتاب صحيح الإمام البخاري رضي الله تعالى عنه   أ.د. يسرى جبر","category":"حديث"},{"id":"jzLcmEUao08","title":"شرح صحيح البخاري كتاب الدعوات (الاستعاذة من أرذل العمر ومن فتنة الدنيا)المجلس السادس د.يسري جبر","publishedAt":"2017-05-14T15:20:43Z","duration":"PT44M4S","thumbnail":"https://i.ytimg.com/vi/jzLcmEUao08/mqdefault.jpg","viewCount":"467","playlistId":"PLEkQk5xrP-tmJuzaj4GWRenFoFx9gdbFX","playlistName":"شرح كتاب صحيح الإمام البخاري رضي الله تعالى عنه   أ.د. يسرى جبر","category":"حديث"},{"id":"p3al_tWSuRs","title":"صحيح الإمام البخاري رضي الله عنه كتاب اللباس ( باب الجعد ) المجلس التاسع. د. يسري جبر","publishedAt":"2016-11-07T19:10:23Z","duration":"PT50M10S","thumbnail":"https://i.ytimg.com/vi/p3al_tWSuRs/mqdefault.jpg","viewCount":"168","playlistId":"PLEkQk5xrP-tmJuzaj4GWRenFoFx9gdbFX","playlistName":"شرح كتاب صحيح الإمام البخاري رضي الله تعالى عنه   أ.د. يسرى جبر","category":"حديث"},{"id":"clUWDYt-S5Q","title":"صحيح الإمام البخاري رضي الله عنه كتاب اللباس ( باب إعْفَاءِ اللِّحى ) المجلس الثامن. د. يسري جبر","publishedAt":"2016-11-06T14:03:06Z","duration":"PT44M","thumbnail":"https://i.ytimg.com/vi/clUWDYt-S5Q/mqdefault.jpg","viewCount":"785","playlistId":"PLEkQk5xrP-tmJuzaj4GWRenFoFx9gdbFX","playlistName":"شرح كتاب صحيح الإمام البخاري رضي الله تعالى عنه   أ.د. يسرى جبر","category":"حديث"},{"id":"l-siBlIVPtY","title":"صحيح الإمام البخاري رضي الله عنه - كتاب الذبائح والصيد والتسمية على الصيد -المجلس الثاني د. يسري جبر","publishedAt":"2016-03-28T05:12:33Z","duration":"PT1H30S","thumbnail":"https://i.ytimg.com/vi/l-siBlIVPtY/mqdefault.jpg","viewCount":"133","playlistId":"PLEkQk5xrP-tmJuzaj4GWRenFoFx9gdbFX","playlistName":"شرح كتاب صحيح الإمام البخاري رضي الله تعالى عنه   أ.د. يسرى جبر","category":"حديث"},{"id":"_o7TCjHNbB4","title":"صحيح الإمام البخاري رضي الله عنه - كتاب الذبائح والصيد والتسمية على الصيد - المجلس الأول د. يسري جبر","publishedAt":"2016-03-27T04:48:15Z","duration":"PT44M43S","thumbnail":"https://i.ytimg.com/vi/_o7TCjHNbB4/mqdefault.jpg","viewCount":"187","playlistId":"PLEkQk5xrP-tmJuzaj4GWRenFoFx9gdbFX","playlistName":"شرح كتاب صحيح الإمام البخاري رضي الله تعالى عنه   أ.د. يسرى جبر","category":"حديث"},{"id":"oLRgNnghg_8","title":"صحيح الإمام البخاري رضي الله تعالى عنه - كتاب العقيقة  د. يسري جبر","publishedAt":"2016-03-21T19:51:56Z","duration":"PT32M43S","thumbnail":"https://i.ytimg.com/vi/oLRgNnghg_8/mqdefault.jpg","viewCount":"199","playlistId":"PLEkQk5xrP-tmJuzaj4GWRenFoFx9gdbFX","playlistName":"شرح كتاب صحيح الإمام البخاري رضي الله تعالى عنه   أ.د. يسرى جبر","category":"حديث"},{"id":"YrFAIynXGms","title":"صحيح الإمام البخاري رضي الله تعالى عنه - كتاب الأطعمة - المجلس التاسع والأخير","publishedAt":"2016-03-19T11:18:16Z","duration":"PT39M55S","thumbnail":"https://i.ytimg.com/vi/YrFAIynXGms/mqdefault.jpg","viewCount":"125","playlistId":"PLEkQk5xrP-tmJuzaj4GWRenFoFx9gdbFX","playlistName":"شرح كتاب صحيح الإمام البخاري رضي الله تعالى عنه   أ.د. يسرى جبر","category":"حديث"},{"id":"WZ8RgU-fZUM","title":"صحيح الإمام البخاري رضي الله تعالى عنه - كتاب الأطعمة - المجلس الثامن","publishedAt":"2016-03-18T14:20:39Z","duration":"PT1H49S","thumbnail":"https://i.ytimg.com/vi/WZ8RgU-fZUM/mqdefault.jpg","viewCount":"124","playlistId":"PLEkQk5xrP-tmJuzaj4GWRenFoFx9gdbFX","playlistName":"شرح كتاب صحيح الإمام البخاري رضي الله تعالى عنه   أ.د. يسرى جبر","category":"حديث"},{"id":"9CUQMs6fPHc","title":"صحيح البخاري كتاب الدعوات -هل يُصلى على غير النبي صلى الله عليه وآله وسلم - المجلس الخامس د.يسري جبر","publishedAt":"2017-05-08T21:03:56Z","duration":"PT1H6M3S","thumbnail":"https://i.ytimg.com/vi/9CUQMs6fPHc/mqdefault.jpg","viewCount":"374","playlistId":"PLEkQk5xrP-tmJuzaj4GWRenFoFx9gdbFX","playlistName":"شرح كتاب صحيح الإمام البخاري رضي الله تعالى عنه   أ.د. يسرى جبر","category":"حديث"},{"id":"cAjtlydGmb0","title":"شرح صحيح الإمام البخاري رضي الله عنه - كتاب الدعوات (الدعاء عند الكرب)المجلس الرابع د. يسري جبر","publishedAt":"2017-05-07T15:30:16Z","duration":"PT37M33S","thumbnail":"https://i.ytimg.com/vi/cAjtlydGmb0/mqdefault.jpg","viewCount":"616","playlistId":"PLEkQk5xrP-tmJuzaj4GWRenFoFx9gdbFX","playlistName":"شرح كتاب صحيح الإمام البخاري رضي الله تعالى عنه   أ.د. يسرى جبر","category":"حديث"}],"total":219,"page":2,"pageSize":24,"totalPages":10}