{"items":[{"id":"HOGWSrespeY","title":"شرح كتاب الزهد من سنن الترمذي - المجلس التاسع","publishedAt":"2016-01-10T08:41:27Z","duration":"PT38M26S","thumbnail":"https://i.ytimg.com/vi/HOGWSrespeY/mqdefault.jpg","viewCount":"239","playlistId":"PLEkQk5xrP-tnu6of679SvxdVx0qSrJzmb","playlistName":"شرح سنن الإمام الترمذي رضى الله عنه د. يسري جبر","category":"متنوع"},{"id":"Uzplm_0g23A","title":"شرح كتاب تفسير القرآن من سنن الترمذي - المجلس الرابع عشر","publishedAt":"2016-04-21T03:18:43Z","duration":"PT29M2S","thumbnail":"https://i.ytimg.com/vi/Uzplm_0g23A/mqdefault.jpg","viewCount":"82","playlistId":"PLEkQk5xrP-tnu6of679SvxdVx0qSrJzmb","playlistName":"شرح سنن الإمام الترمذي رضى الله عنه د. يسري جبر","category":"متنوع"},{"id":"DMVupGvdt6E","title":"شرح كتاب تفسير القرآن من سنن الترمذي - المجلس الثالث عشر","publishedAt":"2016-04-20T03:09:09Z","duration":"PT40M52S","thumbnail":"https://i.ytimg.com/vi/DMVupGvdt6E/mqdefault.jpg","viewCount":"102","playlistId":"PLEkQk5xrP-tnu6of679SvxdVx0qSrJzmb","playlistName":"شرح سنن الإمام الترمذي رضى الله عنه د. يسري جبر","category":"متنوع"},{"id":"3vtbWzLm3aM","title":"شرح كتاب الزهد من سنن الترمذي - المجلس الثامن","publishedAt":"2016-01-09T08:04:52Z","duration":"PT31M17S","thumbnail":"https://i.ytimg.com/vi/3vtbWzLm3aM/mqdefault.jpg","viewCount":"175","playlistId":"PLEkQk5xrP-tnu6of679SvxdVx0qSrJzmb","playlistName":"شرح سنن الإمام الترمذي رضى الله عنه د. يسري جبر","category":"متنوع"},{"id":"OTSt55Cr8dc","title":"شرح كتاب الزهد من سنن الترمذي - المجلس السابع","publishedAt":"2016-01-08T07:44:57Z","duration":"PT36M48S","thumbnail":"https://i.ytimg.com/vi/OTSt55Cr8dc/mqdefault.jpg","viewCount":"127","playlistId":"PLEkQk5xrP-tnu6of679SvxdVx0qSrJzmb","playlistName":"شرح سنن الإمام الترمذي رضى الله عنه د. يسري جبر","category":"متنوع"},{"id":"HoBcUKli7RM","title":"شرح كتاب الزهد من سنن الترمذي - المجلس السادس","publishedAt":"2016-01-07T06:24:19Z","duration":"PT37M1S","thumbnail":"https://i.ytimg.com/vi/HoBcUKli7RM/mqdefault.jpg","viewCount":"164","playlistId":"PLEkQk5xrP-tnu6of679SvxdVx0qSrJzmb","playlistName":"شرح سنن الإمام الترمذي رضى الله عنه د. يسري جبر","category":"متنوع"},{"id":"GhjsVLLOEnk","title":"شرح كتاب الأشربة من سنن الترمذي - المجلس الثالث","publishedAt":"2015-08-27T05:11:22Z","duration":"PT27M40S","thumbnail":"https://i.ytimg.com/vi/GhjsVLLOEnk/mqdefault.jpg","viewCount":"170","playlistId":"PLEkQk5xrP-tnu6of679SvxdVx0qSrJzmb","playlistName":"شرح سنن الإمام الترمذي رضى الله عنه د. يسري جبر","category":"متنوع"},{"id":"BK-LYYCCnzo","title":"شرح كتاب الأشربة من سنن الترمذي - المجلس الثاني","publishedAt":"2015-08-26T05:02:15Z","duration":"PT31M","thumbnail":"https://i.ytimg.com/vi/BK-LYYCCnzo/mqdefault.jpg","viewCount":"137","playlistId":"PLEkQk5xrP-tnu6of679SvxdVx0qSrJzmb","playlistName":"شرح سنن الإمام الترمذي رضى الله عنه د. يسري جبر","category":"متنوع"},{"id":"ABUprosReE4","title":"شرح كتاب الأشربة من سنن الترمذي - المجلس الأول","publishedAt":"2015-08-25T04:54:00Z","duration":"PT28M","thumbnail":"https://i.ytimg.com/vi/ABUprosReE4/mqdefault.jpg","viewCount":"131","playlistId":"PLEkQk5xrP-tnu6of679SvxdVx0qSrJzmb","playlistName":"شرح سنن الإمام الترمذي رضى الله عنه د. يسري جبر","category":"متنوع"},{"id":"Fwiqbr1Fbks","title":"شرح كتاب الأطعمة من سنن الترمذي - المجلس الثامن","publishedAt":"2015-08-24T04:39:16Z","duration":"PT27M47S","thumbnail":"https://i.ytimg.com/vi/Fwiqbr1Fbks/mqdefault.jpg","viewCount":"147","playlistId":"PLEkQk5xrP-tnu6of679SvxdVx0qSrJzmb","playlistName":"شرح سنن الإمام الترمذي رضى الله عنه د. يسري جبر","category":"متنوع"},{"id":"FAP8ZcQj5nA","title":"شرح كتاب تفسير القرآن من سنن الترمذي - المجلس الحادي عشر","publishedAt":"2016-04-19T01:54:58Z","duration":"PT35M21S","thumbnail":"https://i.ytimg.com/vi/FAP8ZcQj5nA/mqdefault.jpg","viewCount":"120","playlistId":"PLEkQk5xrP-tnu6of679SvxdVx0qSrJzmb","playlistName":"شرح سنن الإمام الترمذي رضى الله عنه د. يسري جبر","category":"متنوع"},{"id":"uVsZICF2jKk","title":"شرح كتاب تفسير القرآن من سنن الترمذي - المجلس العاشر","publishedAt":"2016-04-17T05:17:31Z","duration":"PT38M14S","thumbnail":"https://i.ytimg.com/vi/uVsZICF2jKk/mqdefault.jpg","viewCount":"127","playlistId":"PLEkQk5xrP-tnu6of679SvxdVx0qSrJzmb","playlistName":"شرح سنن الإمام الترمذي رضى الله عنه د. يسري جبر","category":"متنوع"},{"id":"qnfeDU1eHpU","title":"شرح كتاب تفسير القرآن من سنن الترمذي - المجلس التاسع","publishedAt":"2016-04-16T20:06:16Z","duration":"PT31M7S","thumbnail":"https://i.ytimg.com/vi/qnfeDU1eHpU/mqdefault.jpg","viewCount":"122","playlistId":"PLEkQk5xrP-tnu6of679SvxdVx0qSrJzmb","playlistName":"شرح سنن الإمام الترمذي رضى الله عنه د. يسري جبر","category":"متنوع"},{"id":"S2FUgPrlFP0","title":"شرح كتاب تفسير القرآن من سنن الترمذي - المجلس الثامن","publishedAt":"2016-04-11T08:35:50Z","duration":"PT28M51S","thumbnail":"https://i.ytimg.com/vi/S2FUgPrlFP0/mqdefault.jpg","viewCount":"149","playlistId":"PLEkQk5xrP-tnu6of679SvxdVx0qSrJzmb","playlistName":"شرح سنن الإمام الترمذي رضى الله عنه د. يسري جبر","category":"متنوع"},{"id":"gkXtyNmcEhQ","title":"شرح كتاب تفسير القرآن من سنن الترمذي - المجلس السابع","publishedAt":"2016-04-10T11:03:24Z","duration":"PT20M22S","thumbnail":"https://i.ytimg.com/vi/gkXtyNmcEhQ/mqdefault.jpg","viewCount":"111","playlistId":"PLEkQk5xrP-tnu6of679SvxdVx0qSrJzmb","playlistName":"شرح سنن الإمام الترمذي رضى الله عنه د. يسري جبر","category":"متنوع"},{"id":"ZsDW_Ot1sMs","title":"شرح كتاب المناقب من سنن الترمذي - المجلس السابع عشر","publishedAt":"2016-07-12T07:03:46Z","duration":"PT13M8S","thumbnail":"https://i.ytimg.com/vi/ZsDW_Ot1sMs/mqdefault.jpg","viewCount":"110","playlistId":"PLEkQk5xrP-tnu6of679SvxdVx0qSrJzmb","playlistName":"شرح سنن الإمام الترمذي رضى الله عنه د. يسري جبر","category":"متنوع"},{"id":"iZli3a-8oyY","title":"شرح كتاب المناقب من سنن الترمذي - المجلس السادس عشر","publishedAt":"2016-07-12T03:26:50Z","duration":"PT11M1S","thumbnail":"https://i.ytimg.com/vi/iZli3a-8oyY/mqdefault.jpg","viewCount":"105","playlistId":"PLEkQk5xrP-tnu6of679SvxdVx0qSrJzmb","playlistName":"شرح سنن الإمام الترمذي رضى الله عنه د. يسري جبر","category":"متنوع"},{"id":"KHxnkeG7UJk","title":"شرح كتاب المناقب من سنن الترمذي - المجلس الخامس عشر","publishedAt":"2016-07-11T21:32:00Z","duration":"PT12M44S","thumbnail":"https://i.ytimg.com/vi/KHxnkeG7UJk/mqdefault.jpg","viewCount":"110","playlistId":"PLEkQk5xrP-tnu6of679SvxdVx0qSrJzmb","playlistName":"شرح سنن الإمام الترمذي رضى الله عنه د. يسري جبر","category":"متنوع"},{"id":"N9udXmhA7yA","title":"شرح كتاب الأحكام من سنن الترمذي - المجلس السادس","publishedAt":"2015-06-13T04:08:19Z","duration":"PT32M39S","thumbnail":"https://i.ytimg.com/vi/N9udXmhA7yA/mqdefault.jpg","viewCount":"118","playlistId":"PLEkQk5xrP-tnu6of679SvxdVx0qSrJzmb","playlistName":"شرح سنن الإمام الترمذي رضى الله عنه د. يسري جبر","category":"متنوع"},{"id":"qsFtjiofItc","title":"شرح كتاب الأحكام من سنن الترمذي - المجلس الخامس","publishedAt":"2015-06-12T04:10:07Z","duration":"PT27M22S","thumbnail":"https://i.ytimg.com/vi/qsFtjiofItc/mqdefault.jpg","viewCount":"141","playlistId":"PLEkQk5xrP-tnu6of679SvxdVx0qSrJzmb","playlistName":"شرح سنن الإمام الترمذي رضى الله عنه د. يسري جبر","category":"متنوع"},{"id":"lHYTWF1Ypk8","title":"شرح كتاب الزهد من سنن الترمذي - المجلس الخامس","publishedAt":"2016-01-06T06:17:06Z","duration":"PT37M59S","thumbnail":"https://i.ytimg.com/vi/lHYTWF1Ypk8/mqdefault.jpg","viewCount":"188","playlistId":"PLEkQk5xrP-tnu6of679SvxdVx0qSrJzmb","playlistName":"شرح سنن الإمام الترمذي رضى الله عنه د. يسري جبر","category":"متنوع"},{"id":"viLCUlYrSas","title":"شرح كتاب الزهد من سنن الترمذي - المجلس الرابع","publishedAt":"2016-01-05T06:03:10Z","duration":"PT31M51S","thumbnail":"https://i.ytimg.com/vi/viLCUlYrSas/mqdefault.jpg","viewCount":"186","playlistId":"PLEkQk5xrP-tnu6of679SvxdVx0qSrJzmb","playlistName":"شرح سنن الإمام الترمذي رضى الله عنه د. يسري جبر","category":"متنوع"},{"id":"QX3UPs20D4g","title":"شرح كتاب الزهد من سنن الترمذي - المجلس الثالث","publishedAt":"2016-01-04T20:39:45Z","duration":"PT12M18S","thumbnail":"https://i.ytimg.com/vi/QX3UPs20D4g/mqdefault.jpg","viewCount":"114","playlistId":"PLEkQk5xrP-tnu6of679SvxdVx0qSrJzmb","playlistName":"شرح سنن الإمام الترمذي رضى الله عنه د. يسري جبر","category":"متنوع"},{"id":"8cI5GlgzRHk","title":"شرح كتاب الزهد من سنن الترمذي - المجلس الثاني","publishedAt":"2016-01-03T06:08:01Z","duration":"PT31M41S","thumbnail":"https://i.ytimg.com/vi/8cI5GlgzRHk/mqdefault.jpg","viewCount":"200","playlistId":"PLEkQk5xrP-tnu6of679SvxdVx0qSrJzmb","playlistName":"شرح سنن الإمام الترمذي رضى الله عنه د. يسري جبر","category":"متنوع"}],"total":244,"page":4,"pageSize":24,"totalPages":11}