{"items":[{"id":"RdHnbGKnC3E","title":"شرح صحيح البخاري - كتاب الوصايا من باب ٩","publishedAt":"2017-07-18T15:26:57Z","duration":"PT23M38S","thumbnail":"https://i.ytimg.com/vi/RdHnbGKnC3E/mqdefault.jpg","viewCount":"554","playlistId":"PLEkQk5xrP-tlEerGoLa1AFy-2XvQ-sovv","playlistName":"شرح صحيح البخاري - أ.د. يسري جبر (كاملا)","category":"حديث"},{"id":"848OtqTdwBg","title":"شرح صحيح البخاري - كتاب الوصايا من باب ٥","publishedAt":"2017-07-17T14:20:12Z","duration":"PT21M54S","thumbnail":"https://i.ytimg.com/vi/848OtqTdwBg/mqdefault.jpg","viewCount":"511","playlistId":"PLEkQk5xrP-tlEerGoLa1AFy-2XvQ-sovv","playlistName":"شرح صحيح البخاري - أ.د. يسري جبر (كاملا)","category":"حديث"},{"id":"WkXPYPsrGdQ","title":"شرح صحيح البخاري - كتاب الوصايا من أوله","publishedAt":"2017-07-10T17:24:15Z","duration":"PT24M4S","thumbnail":"https://i.ytimg.com/vi/WkXPYPsrGdQ/mqdefault.jpg","viewCount":"709","playlistId":"PLEkQk5xrP-tlEerGoLa1AFy-2XvQ-sovv","playlistName":"شرح صحيح البخاري - أ.د. يسري جبر (كاملا)","category":"حديث"},{"id":"Rpd3PrA8l9E","title":"شرح صحيح البخاري - كتاب الشروط من باب 19","publishedAt":"2017-07-09T18:25:21Z","duration":"PT20M29S","thumbnail":"https://i.ytimg.com/vi/Rpd3PrA8l9E/mqdefault.jpg","viewCount":"530","playlistId":"PLEkQk5xrP-tlEerGoLa1AFy-2XvQ-sovv","playlistName":"شرح صحيح البخاري - أ.د. يسري جبر (كاملا)","category":"حديث"},{"id":"K7foAwLzvBw","title":"شرح صحيح البخاري - كتاب الشروط من باب ١٤","publishedAt":"2017-07-08T17:37:10Z","duration":"PT45M9S","thumbnail":"https://i.ytimg.com/vi/K7foAwLzvBw/mqdefault.jpg","viewCount":"658","playlistId":"PLEkQk5xrP-tlEerGoLa1AFy-2XvQ-sovv","playlistName":"شرح صحيح البخاري - أ.د. يسري جبر (كاملا)","category":"حديث"},{"id":"53LJFgpyb9M","title":"شرح صحيح البخاري - كتاب الشروط من باب ٦","publishedAt":"2017-07-07T14:37:39Z","duration":"PT28M10S","thumbnail":"https://i.ytimg.com/vi/53LJFgpyb9M/mqdefault.jpg","viewCount":"585","playlistId":"PLEkQk5xrP-tlEerGoLa1AFy-2XvQ-sovv","playlistName":"شرح صحيح البخاري - أ.د. يسري جبر (كاملا)","category":"حديث"},{"id":"u3wO-Rf0LeI","title":"شرح صحيح البخاري - كتاب الشروط من أوله","publishedAt":"2017-07-06T14:43:33Z","duration":"PT35M42S","thumbnail":"https://i.ytimg.com/vi/u3wO-Rf0LeI/mqdefault.jpg","viewCount":"730","playlistId":"PLEkQk5xrP-tlEerGoLa1AFy-2XvQ-sovv","playlistName":"شرح صحيح البخاري - أ.د. يسري جبر (كاملا)","category":"حديث"},{"id":"uOO9wgBHPZA","title":"شرح صحيح البخاري - كتاب الصلح من باب ١٠","publishedAt":"2017-07-05T16:02:40Z","duration":"PT28M15S","thumbnail":"https://i.ytimg.com/vi/uOO9wgBHPZA/mqdefault.jpg","viewCount":"609","playlistId":"PLEkQk5xrP-tlEerGoLa1AFy-2XvQ-sovv","playlistName":"شرح صحيح البخاري - أ.د. يسري جبر (كاملا)","category":"حديث"},{"id":"r6Rt0DUvRsk","title":"شرح صحيح البخاري - كتاب الصلح من باب ٧","publishedAt":"2017-07-04T11:38:58Z","duration":"PT19M37S","thumbnail":"https://i.ytimg.com/vi/r6Rt0DUvRsk/mqdefault.jpg","viewCount":"533","playlistId":"PLEkQk5xrP-tlEerGoLa1AFy-2XvQ-sovv","playlistName":"شرح صحيح البخاري - أ.د. يسري جبر (كاملا)","category":"حديث"},{"id":"NgbYq2zd0fg","title":"شرح صحيح البخاري - كتاب الصلح من باب ٥","publishedAt":"2017-07-03T17:39:23Z","duration":"PT34M40S","thumbnail":"https://i.ytimg.com/vi/NgbYq2zd0fg/mqdefault.jpg","viewCount":"632","playlistId":"PLEkQk5xrP-tlEerGoLa1AFy-2XvQ-sovv","playlistName":"شرح صحيح البخاري - أ.د. يسري جبر (كاملا)","category":"حديث"},{"id":"HSrUszoWypQ","title":"شرح صحيح البخاري - كتاب الصلح من أوله","publishedAt":"2017-07-01T20:36:03Z","duration":"PT20M40S","thumbnail":"https://i.ytimg.com/vi/HSrUszoWypQ/mqdefault.jpg","viewCount":"681","playlistId":"PLEkQk5xrP-tlEerGoLa1AFy-2XvQ-sovv","playlistName":"شرح صحيح البخاري - أ.د. يسري جبر (كاملا)","category":"حديث"},{"id":"tfW3UOZFcOQ","title":"شرح صحيح البخاري - كتاب الشهادات من باب ٣٠","publishedAt":"2017-06-30T20:08:18Z","duration":"PT21M38S","thumbnail":"https://i.ytimg.com/vi/tfW3UOZFcOQ/mqdefault.jpg","viewCount":"535","playlistId":"PLEkQk5xrP-tlEerGoLa1AFy-2XvQ-sovv","playlistName":"شرح صحيح البخاري - أ.د. يسري جبر (كاملا)","category":"حديث"},{"id":"oO1H1QBi5lA","title":"شرح صحيح البخاري - كتاب الشهادات من باب ٢٢","publishedAt":"2017-06-28T19:24:41Z","duration":"PT33M46S","thumbnail":"https://i.ytimg.com/vi/oO1H1QBi5lA/mqdefault.jpg","viewCount":"707","playlistId":"PLEkQk5xrP-tlEerGoLa1AFy-2XvQ-sovv","playlistName":"شرح صحيح البخاري - أ.د. يسري جبر (كاملا)","category":"حديث"},{"id":"DfELSHLXOSA","title":"شرح صحيح البخاري - كتاب الشهادات من باب ١٦","publishedAt":"2017-06-26T18:48:24Z","duration":"PT27M1S","thumbnail":"https://i.ytimg.com/vi/DfELSHLXOSA/mqdefault.jpg","viewCount":"670","playlistId":"PLEkQk5xrP-tlEerGoLa1AFy-2XvQ-sovv","playlistName":"شرح صحيح البخاري - أ.د. يسري جبر (كاملا)","category":"حديث"},{"id":"cddWFC7FSeQ","title":"شرح صحيح البخاري - كتاب الشهادات من باب ١٥","publishedAt":"2017-06-24T22:31:51Z","duration":"PT33M58S","thumbnail":"https://i.ytimg.com/vi/cddWFC7FSeQ/mqdefault.jpg","viewCount":"602","playlistId":"PLEkQk5xrP-tlEerGoLa1AFy-2XvQ-sovv","playlistName":"شرح صحيح البخاري - أ.د. يسري جبر (كاملا)","category":"حديث"},{"id":"WUgm144jWVs","title":"شرح صحيح البخاري - كتاب الشهادات من باب ١٢","publishedAt":"2017-06-23T17:19:10Z","duration":"PT15M45S","thumbnail":"https://i.ytimg.com/vi/WUgm144jWVs/mqdefault.jpg","viewCount":"535","playlistId":"PLEkQk5xrP-tlEerGoLa1AFy-2XvQ-sovv","playlistName":"شرح صحيح البخاري - أ.د. يسري جبر (كاملا)","category":"حديث"},{"id":"qbAe8YqvjsI","title":"شرح صحيح البخاري - كتاب الشهادات من باب ٨","publishedAt":"2017-06-22T17:31:48Z","duration":"PT41M21S","thumbnail":"https://i.ytimg.com/vi/qbAe8YqvjsI/mqdefault.jpg","viewCount":"634","playlistId":"PLEkQk5xrP-tlEerGoLa1AFy-2XvQ-sovv","playlistName":"شرح صحيح البخاري - أ.د. يسري جبر (كاملا)","category":"حديث"},{"id":"3a1DhC3QgWU","title":"شرح صحيح البخاري - كتاب الشهادات من باب ٥","publishedAt":"2017-06-21T18:34:54Z","duration":"PT20M47S","thumbnail":"https://i.ytimg.com/vi/3a1DhC3QgWU/mqdefault.jpg","viewCount":"581","playlistId":"PLEkQk5xrP-tlEerGoLa1AFy-2XvQ-sovv","playlistName":"شرح صحيح البخاري - أ.د. يسري جبر (كاملا)","category":"حديث"},{"id":"CVSMyRAp1y0","title":"شرح صحيح البخاري - كتاب أحاديث الأنبياء من أوله","publishedAt":"2017-09-25T14:47:02Z","duration":"PT37M22S","thumbnail":"https://i.ytimg.com/vi/CVSMyRAp1y0/mqdefault.jpg","viewCount":"1070","playlistId":"PLEkQk5xrP-tlEerGoLa1AFy-2XvQ-sovv","playlistName":"شرح صحيح البخاري - أ.د. يسري جبر (كاملا)","category":"حديث"},{"id":"74qFinaitS0","title":"شرح صحيح البخاري - كتاب بدء الخلق من باب ١٥","publishedAt":"2017-09-20T19:16:00Z","duration":"PT45M41S","thumbnail":"https://i.ytimg.com/vi/74qFinaitS0/mqdefault.jpg","viewCount":"733","playlistId":"PLEkQk5xrP-tlEerGoLa1AFy-2XvQ-sovv","playlistName":"شرح صحيح البخاري - أ.د. يسري جبر (كاملا)","category":"حديث"},{"id":"06cuLnQfC94","title":"شرح صحيح البخاري - كتاب بدء الخلق من باب ١٣","publishedAt":"2017-09-20T19:13:56Z","duration":"PT37M57S","thumbnail":"https://i.ytimg.com/vi/06cuLnQfC94/mqdefault.jpg","viewCount":"733","playlistId":"PLEkQk5xrP-tlEerGoLa1AFy-2XvQ-sovv","playlistName":"شرح صحيح البخاري - أ.د. يسري جبر (كاملا)","category":"حديث"},{"id":"EQ1His7qc68","title":"شرح صحيح البخاري - كتاب بدء الخلق من باب ١١ من حديث محمد ابن يوسف","publishedAt":"2017-09-19T22:15:00Z","duration":"PT37M15S","thumbnail":"https://i.ytimg.com/vi/EQ1His7qc68/mqdefault.jpg","viewCount":"793","playlistId":"PLEkQk5xrP-tlEerGoLa1AFy-2XvQ-sovv","playlistName":"شرح صحيح البخاري - أ.د. يسري جبر (كاملا)","category":"حديث"},{"id":"ICbFPy1_7wc","title":"شرح صحيح البخاري - كتاب بدء الخلق من باب ١١ من حديث محمد","publishedAt":"2017-09-18T13:57:04Z","duration":"PT35M57S","thumbnail":"https://i.ytimg.com/vi/ICbFPy1_7wc/mqdefault.jpg","viewCount":"367","playlistId":"PLEkQk5xrP-tlEerGoLa1AFy-2XvQ-sovv","playlistName":"شرح صحيح البخاري - أ.د. يسري جبر (كاملا)","category":"حديث"},{"id":"WYN-sC6YY08","title":"شرح صحيح البخاري - كتاب بدء الخلق من باب ١١","publishedAt":"2017-09-17T21:54:15Z","duration":"PT37M7S","thumbnail":"https://i.ytimg.com/vi/WYN-sC6YY08/mqdefault.jpg","viewCount":"430","playlistId":"PLEkQk5xrP-tlEerGoLa1AFy-2XvQ-sovv","playlistName":"شرح صحيح البخاري - أ.د. يسري جبر (كاملا)","category":"حديث"}],"total":719,"page":21,"pageSize":24,"totalPages":30}